halchemy/__init__.py
halchemy/api.py
halchemy/configuration.py
halchemy/error_handling.py
halchemy/follower.py
halchemy/http_model.py
halchemy/json_type.py
halchemy/requester.py
halchemy/requests_helper.py
halchemy/resource.py
halchemy/status_codes.py
halchemy-1.0.5.dist-info/METADATA
halchemy-1.0.5.dist-info/WHEEL
halchemy-1.0.5.dist-info/top_level.txt
halchemy-1.0.5.dist-info/RECORD
