Metadata-Version: 2.2
Name: halchemy
Version: 1.0.5
Summary: HAL for humans
Home-page: https://github.com/pointw-dev/halchemy
Author: Michael Ottoson
Author-email: michael@pointw.com
License: MIT
Project-URL: Documentation, https://pointw-dev.github.io/halchemy
Classifier: Development Status :: 5 - Production/Stable
Classifier: License :: OSI Approved :: MIT License
Classifier: Programming Language :: Python :: 3
Classifier: Operating System :: OS Independent
Classifier: Intended Audience :: Developers
Classifier: Topic :: Internet :: WWW/HTTP
Classifier: Topic :: Utilities
Requires-Dist: requests
Requires-Dist: uritemplate
Dynamic: author
Dynamic: author-email
Dynamic: classifier
Dynamic: description
Dynamic: description-content-type
Dynamic: home-page
Dynamic: license
Dynamic: project-url
Dynamic: requires-dist
Dynamic: summary
